mathutils/__init__.py
mathutils/operations.py
mathutilsVV-0.1.1.dist-info/LICENSE
mathutilsVV-0.1.1.dist-info/METADATA
mathutilsVV-0.1.1.dist-info/WHEEL
mathutilsVV-0.1.1.dist-info/top_level.txt
mathutilsVV-0.1.1.dist-info/RECORD
